iedb/__init__.py
iedb/api.py
tests/__init__.py
tests/test_api.py
iedb-0.0.2.dist-info/LICENSE
iedb-0.0.2.dist-info/METADATA
iedb-0.0.2.dist-info/WHEEL
iedb-0.0.2.dist-info/top_level.txt
iedb-0.0.2.dist-info/RECORD
