Metadata-Version: 2.1
Name: iedb
Version: 0.0.2
Summary: Python SDK for IEDB Tools API. Full details can be found at     http://tools.iedb.org/main/tools-api/
Home-page: http://packages.python.org/iedb
Author: Matt Femia
License: MIT
Keywords: iedb mhc mhc-binding t-cell epitope mhc-i mhc-ii hla
Platform: UNKNOWN
Classifier: Development Status :: 3 - Alpha
Classifier: Topic :: Utilities
Classifier: Operating System :: OS Independent
Requires-Python: >=3.6
Requires-Dist: pandas (>=1.0.0)
Requires-Dist: requests (>=2.22.0)
